pgn_tokenizer/__init__.py
pgn_tokenizer/constants.py
pgn_tokenizer/py.typed
pgn_tokenizer/config/__init__.py
pgn_tokenizer/config/pgn-tokenizer-merges.txt
pgn_tokenizer/config/pgn-tokenizer-vocab.json
pgn_tokenizer/config/pgn-tokenizer.json
pgn_tokenizer-0.1.3.dist-info/METADATA
pgn_tokenizer-0.1.3.dist-info/WHEEL
pgn_tokenizer-0.1.3.dist-info/entry_points.txt
pgn_tokenizer-0.1.3.dist-info/licenses/LICENSE
pgn_tokenizer-0.1.3.dist-info/RECORD
