Metadata-Version: 2.4
Name: pgn-tokenizer
Version: 0.1.3
Summary: A byte pair encoding tokenizer for chess portable game notation (PGN)
Project-URL: Homepage, https://github.com/DVDAGames/pgn-tokenizer
Project-URL: Documentation, https://github.com/DVDAGames/pgn-tokenizer
Project-URL: Repository, https://github.com/DVDAGames/pgn-tokenizer.git
Project-URL: Issues, https://github.com/DVDAGames/pgn-tokenizer.git/issues
Project-URL: Changelog, https://github.com/DVDAGames/pgn-tokenizer.git/blob/master/CHANGELOG.md
Author-email: Eric allen <eric@ericrallen.dev>
License-Expression: MIT
License-File: LICENSE
Keywords: bpe,byte pair encoding,chess,llm,pgn,tokenizer,tokenizers
Classifier: Development Status :: 4 - Beta
Classifier: Intended Audience :: Developers
Classifier: Programming Language :: Python :: 3
Classifier: Programming Language :: Python :: 3.10
Classifier: Programming Language :: Python :: 3.11
Classifier: Programming Language :: Python :: 3.12
Classifier: Programming Language :: Python :: 3.13
Classifier: Topic :: Games/Entertainment :: Board Games
Classifier: Topic :: Software Development :: Build Tools
Classifier: Topic :: Utilities
Requires-Python: >=3.10
Requires-Dist: transformers>=4.48.1
